<Properties StartupConfiguration="{5F143CBE-0539-43EF-BAE9-F61B70C48CB3}|Default" NuGet.AddPackagesDialog.IncludePrerelease="True">
  <MonoDevelop.Ide.Workbench ActiveDocument="Setlist/MainWindow.cs">
    <Files>
      <File FileName="Setlist/MainWindow.cs" Line="245" Column="10" />
      <File FileName="../DataCollector/DataCollector/Program.cs" Line="75" Column="36" />
      <File FileName="Setlist/Globals.cs" Line="9" Column="62" />
      <File FileName="Setlist/ArtistInfo.cs" Line="17" Column="32" />
      <File FileName="Setlist/SetlistInfo.cs" Line="18" Column="42" />
    </Files>
    <Pads>
      <Pad Id="ProjectPad">
        <State name="__root__">
          <Node name="Setlist" expanded="True">
            <Node name="Setlist" expanded="True">
              <Node name="MainWindow.cs" selected="True" />
            </Node>
          </Node>
        </State>
      </Pad>
      <Pad Id="ClassPad">
        <State name="__root__">
          <Node name="Setlist" expanded="True" selected="True" />
        </State>
      </Pad>
    </Pads>
  </MonoDevelop.Ide.Workbench>
  <MonoDevelop.Ide.ItemProperties.Setlist PreferredExecutionTarget="MonoDevelop.Default" />
  <MonoDevelop.Ide.DebuggingService.PinnedWatches />
  <MonoDevelop.Ide.Workspace ActiveConfiguration="Debug|x86" />
  <MonoDevelop.Ide.DebuggingService.Breakpoints>
    <BreakpointStore />
  </MonoDevelop.Ide.DebuggingService.Breakpoints>
  <MultiItemStartupConfigurations />
</Properties>